formidable/__init__.py
formidable/accesses.py
formidable/app.py
formidable/constants.py
formidable/exception_handler.py
formidable/exceptions.py
formidable/models.py
formidable/permissions.py
formidable/register.py
formidable/security.py
formidable/urls.py
formidable/utils.py
formidable/validators.py
formidable/views.py
formidable/forms/__init__.py
formidable/forms/boundfield.py
formidable/forms/conditions.py
formidable/forms/field_builder.py
formidable/forms/fields.py
formidable/forms/widgets.py
formidable/forms/validations/__init__.py
formidable/json_migrations/0001_add_version.py
formidable/json_migrations/0002_rename_helptext_to_description.py
formidable/json_migrations/0003_uncontextualize_schema.py
formidable/json_migrations/0004_add_conditions.py
formidable/json_migrations/0005_drop_presets.py
formidable/json_migrations/__init__.py
formidable/json_migrations/utils.py
formidable/migrations/0001_initial.py
formidable/migrations/0002_remove_access_display.py
formidable/migrations/0003_item_label_no_size_limit.py
formidable/migrations/0004_formidable_conditions.py
formidable/migrations/0005_conditions_default.py
formidable/migrations/0006_drop_preset_fields.py
formidable/migrations/0007_drop_preset_tables.py
formidable/migrations/0008_formidable_item_value_field_size.py
formidable/migrations/0009_field_parameters.py
formidable/migrations/0010_auto_20200213_1010.py
formidable/migrations/0011_allow_empty_description.py
formidable/migrations/__init__.py
formidable/serializers/__init__.py
formidable/serializers/access.py
formidable/serializers/child_proxy.py
formidable/serializers/common.py
formidable/serializers/defaults.py
formidable/serializers/fields.py
formidable/serializers/forms.py
formidable/serializers/items.py
formidable/serializers/list.py
formidable/serializers/validation.py
django_formidable-7.2.0.dist-info/LICENSE
django_formidable-7.2.0.dist-info/METADATA
django_formidable-7.2.0.dist-info/WHEEL
django_formidable-7.2.0.dist-info/top_level.txt
django_formidable-7.2.0.dist-info/RECORD
