Metadata-Version: 2.1
Name: django-formidable
Version: 7.2.0
Summary: django-formidable is a full django application which allows you to create, edit, delete and use forms.
Home-page: https://github.com/peopledoc/django-formidable
Author: Guillaume Camera, Guillaume Gérard
Author-email: guillaume.camera@people-doc.com, guillaume.gerard@people-doc.com
License: MIT License
Platform: UNKNOWN
Classifier: Environment :: Web Environment
Classifier: Framework :: Django
Classifier: Operating System :: OS Independent
Classifier: Programming Language :: Python
Classifier: Programming Language :: Python :: 3
Classifier: Programming Language :: Python :: 3.6
Classifier: Programming Language :: Python :: 3.7
Classifier: Programming Language :: Python :: 3.8
Classifier: Topic :: Internet :: WWW/HTTP
Classifier: Topic :: Internet :: WWW/HTTP :: Dynamic Content
Requires-Python: >=3.6
Requires-Dist: Django
Requires-Dist: djangorestframework (<4.0.0)
Requires-Dist: jsonfield
Requires-Dist: markdown
Requires-Dist: python-dateutil
Requires-Dist: pytz
